{
    "fluentMethods": true,
    "relationships": [
        {
            "relationshipType": "many-to-many",
            "otherEntityRelationshipName": "product",
            "relationshipName": "category",
            "otherEntityName": "category",
            "otherEntityField": "id",
            "ownerSide": true
        },
        {
            "relationshipType": "many-to-one",
            "relationshipName": "order",
            "otherEntityName": "order",
            "otherEntityField": "id"
        }
    ],
    "fields": [
        {
            "fieldName": "name",
            "fieldType": "String"
        },
        {
            "fieldName": "description",
            "fieldType": "String"
        },
        {
            "fieldName": "image",
            "fieldType": "byte[]",
            "fieldTypeBlobContent": "image"
        },
        {
            "fieldName": "price",
            "fieldType": "BigDecimal"
        }
    ],
    "changelogDate": "20170806204713",
    "entityTableName": "product",
    "dto": "no",
    "pagination": "no",
    "service": "no"
}